[{"name":"Silhouettes","artists":"Herman's Hermits","duration":"121040","album":"The Very Best Of Herman's Hermits","releaseDate":"1996-03-06","previewUrl":"null","popularity":18,"explicit":false},{"name":"I'll Never Find Another You","artists":"The Seekers","duration":"162320","album":"The Seekers","releaseDate":"1989-01-30","previewUrl":"https://p.scdn.co/mp3-preview/40154edbaa99b8d9f41370b7837171c067d911a5?cid=67acaa8156c34bd887b0d08fd7a09fc5","popularity":51,"explicit":false},{"name":"Cara mia","artists":"Jay & The Americans","duration":"152093","album":"Cara Mia","releaseDate":"2015-02-28","previewUrl":"https://p.scdn.co/mp3-preview/0b11899088aeeb90757eb4b61f02dd4dcbc3213a?cid=67acaa8156c34bd887b0d08fd7a09fc5","popularity":0,"explicit":false},{"name":"Mr. Tambourine Man","artists":"The Byrds","duration":"149466","album":"Mr. Tambourine Man","releaseDate":"1965-06-21","previewUrl":"https://p.scdn.co/mp3-preview/889919bd8b2121d9fe4382d8cfda8ddbfc7f6570?cid=67acaa8156c34bd887b0d08fd7a09fc5","popularity":61,"explicit":false},{"name":"Cast Your Fate to the Wind","artists":"Sounds Orchestral","duration":"195000","album":"Cast Your Fate to the Wind","releaseDate":"1965-06-05","previewUrl":"https://p.scdn.co/mp3-preview/1feeb63843239fbf828264d92bb89d730b034585?cid=67acaa8156c34bd887b0d08fd7a09fc5","popularity":0,"explicit":false},{"name":"Yes, I'm Ready","artists":"Barbara Mason","duration":"184333","album":"Yes I'm Ready","releaseDate":"1965-01-01","previewUrl":"https://p.scdn.co/mp3-preview/2469c183d0375c30bc5a66acd1e84c094381ec67?cid=67acaa8156c34bd887b0d08fd7a09fc5","popularity":56,"explicit":false},{"name":"What's New Pussycat?","artists":"Tom Jones","duration":"128132","album":"It's Not Unusual","releaseDate":"1987-01-01","previewUrl":"null","popularity":0,"explicit":false},{"name":"Eve Of Destruction","artists":"Barry McGuire","duration":"215826","album":"Eve Of Destruction","releaseDate":"1965-01-01","previewUrl":"null","popularity":55,"explicit":false},{"name":"Hang on Sloopy","artists":"The McCoys","duration":"181733","album":"Hang on Sloopy","releaseDate":"1965","previewUrl":"https://p.scdn.co/mp3-preview/dbda36e25e722f7367a6e69f0c581cc087c8b825?cid=67acaa8156c34bd887b0d08fd7a09fc5","popularity":30,"explicit":false},{"name":"Ticket To Ride - Remastered","artists":"The Beatles","duration":"189680","album":"Help! (Remastered)","releaseDate":"1965-08-06","previewUrl":"null","popularity":0,"explicit":false}]